opymizator/__init__.py
opymizator/main.py
opymizator-0.2.1.dist-info/LICENSE
opymizator-0.2.1.dist-info/METADATA
opymizator-0.2.1.dist-info/WHEEL
opymizator-0.2.1.dist-info/entry_points.txt
opymizator-0.2.1.dist-info/RECORD
